coveo_styles/__init__.py
coveo_styles/py.typed
coveo_styles/styles.py
coveo_styles-3.0.dist-info/METADATA
coveo_styles-3.0.dist-info/WHEEL
coveo_styles-3.0.dist-info/RECORD
