Metadata-Version: 2.1
Name: coveo-styles
Version: 3.0
Summary: Styles, colors and emojis for the command line.
Home-page: https://github.com/coveooss/coveo-python-oss/tree/main/coveo-styles
License: Apache-2.0
Author: Jonathan Piché
Author-email: tools@coveo.com
Requires-Python: >=3.9,<4
Classifier: License :: OSI Approved :: Apache Software License
Classifier: Programming Language :: Python :: 3
Classifier: Programming Language :: Python :: 3.9
Classifier: Programming Language :: Python :: 3.10
Classifier: Programming Language :: Python :: 3.11
Requires-Dist: click (>=8.1)
Requires-Dist: emoji (>=2)
Requires-Dist: typing_extensions
Project-URL: Repository, https://github.com/coveooss/coveo-python-oss/tree/main/coveo-styles
